coochie/__init__.py
coochie/coochie.py
coochie-0.0.1.dist-info/METADATA
coochie-0.0.1.dist-info/WHEEL
coochie-0.0.1.dist-info/top_level.txt
coochie-0.0.1.dist-info/RECORD
