Metadata-Version: 2.1
Name: coochie
Version: 0.0.1
Summary: basic coochie package
Author: zt (x8g)
Author-email: <emailspammerv1@gmail.com>
Keywords: python,coochie
Classifier: Development Status :: 1 - Planning
Classifier: Intended Audience :: Developers
Classifier: Programming Language :: Python :: 3
Classifier: Operating System :: Unix
Classifier: Operating System :: MacOS :: MacOS X
Classifier: Operating System :: Microsoft :: Windows
Requires-Dist: requests
